emzed_ext_mzmine2/__init__.py
emzed_ext_mzmine2/_exceptions.py
emzed_ext_mzmine2/_installers.py
emzed_ext_mzmine2/_java_utils.py
emzed_ext_mzmine2/_mzmine2_default_adducts.json
emzed_ext_mzmine2/_mzmine2_parameter_classes.json
emzed_ext_mzmine2/_parameters.py
emzed_ext_mzmine2/_peak_resolvers.py
emzed_ext_mzmine2/_utils.py
emzed_ext_mzmine2/adduct_search.py
emzed_ext_mzmine2/fragment_search.py
emzed_ext_mzmine2/isotope_grouper.py
emzed_ext_mzmine2/join_aligner.py
emzed_ext_mzmine2/pick_peaks.py
emzed_ext_mzmine2/remove_shoulder_peaks.py
emzed_ext_mzmine2/java/extensions.jar
emzed_ext_mzmine2-3.0.0a4.dist-info/METADATA
emzed_ext_mzmine2-3.0.0a4.dist-info/WHEEL
emzed_ext_mzmine2-3.0.0a4.dist-info/top_level.txt
emzed_ext_mzmine2-3.0.0a4.dist-info/RECORD
