Metadata-Version: 2.4
Name: emzed_ext_mzmine2
Version: 3.0.0a4
Summary: emzed extension to access some algorithms from mzmine2
Author-email: Uwe Schmitt <uwe.schmitt@id.ethz.ch>
License: MIT
Requires-Python: <3.13,>=3.10
Requires-Dist: requests
Requires-Dist: emzed>=3.0.0a1
